{
  "$schema": "https://developer.microsoft.com/json-schemas/spfx/client-side-web-part-manifest.schema.json",
  "id": "b5cbff1c-59e0-4c56-925c-0fc941adda77",
  "alias": "GlpiPhonesWebPart",
  "componentType": "WebPart",
  "version": "*",
  "manifestVersion": 2,
  "requiresCustomScript": false,
  "supportedHosts": [
    "SharePointWebPart",
    "TeamsPersonalApp",
    "TeamsTab",
    "SharePointFullPage"
  ],
  "supportsThemeVariants": true,
  "preconfiguredEntries": [
    {
      "groupId": "5c03119e-3074-46fd-976b-c60198311f70",
      "group": {
        "default": "Advanced"
      },
      "title": {
        "default": "Linhas Bel - GLPI"
      },
      "description": {
        "default": "Linhas móveis Bel - Fonte: https://glpi.bel.ind.br/glpi"
      },
      "officeFabricIconFontName": "CellPhone",
      "fullPageAppIconImageUrl": "assets\\LOGO.png",
      "properties": {
        "description": "Linhas Bel - GLPI"
      }
    }
  ]
}